{
  "author": "marketplaceteam@hubspot.com",
  "author_at": 1535029278517,
  "cdn_purge_embargo_time": 1535029578505,
  "contains_overridable_hubl_tags": true,
  "content_tags": [
    {
      "name": "COMMERCE",
      "source": "MARKETPLACE"
    },
    {
      "name": "COMPATIBLE_ANY",
      "source": "MARKETPLACE"
    },
    {
      "name": "OTHER_INDUSTRY",
      "source": "MARKETPLACE"
    }
  ],
  "created": 1535029267570,
  "css_assets": [],
  "default": true,
  "deleted_at": 0,
  "editable_contexts": [],
  "external_js": [],
  "extra_classes": "widget-type-text",
  "folder_id": 6098902230,
  "global": false,
  "help_text": "",
  "host_template_types": [
    "ANY"
  ],
  "icon": "https://cdn2.hubspotqa.com/hubfs/99263981/high-text.svg",
  "id": 6098194723,
  "is_available_for_new_content": true,
  "is_buffered": false,
  "js_assets": [],
  "label": "One Line of Text",
  "marketplace_version": 78,
  "module_id": 1843376,
  "name": "One Line of Text",
  "other_assets": [],
  "placement_rules": [],
  "portal_id": 123,
  "purchased": false,
  "schema_version": 2,
  "smart_type": "NOT_SMART",
  "tags": [
    "DEFAULT"
  ],
  "updated": 1535029278517,
  "widget_label": "Text",
  "writeable": false
}